<?xml version='1.0' encoding='UTF-8'?>
<song xmlns="http://openlyrics.info/namespace/2009/song" version="0.8" createdIn="OpenLP 2.4.6" modifiedIn="OpenLP 2.4.6" modifiedDate="2021-11-21T08:34:34">
  <properties>
    <titles>
      <title> إتبناني رضي بي</title>
    </titles>
    <comments>
      <comment>Unverfied Collection, Sourced From The Internet by Bill, On 20/11/2021 Contact Email:myway880@gmail.com
</comment>
    </comments>
    <authors>
      <author type="words">In Progress Collection</author>
    </authors>
  </properties>
  <lyrics>
    <verse name="v1a">
      <lines>إتبناني رضي بي<br/>واشتراني حن علي</lines>
    </verse>
    <verse name="v1b">
      <lines>بقالي في حضنه مكان<br/>ونسيت أيام الحرمان<br/>دا أهلي وعيلتي كمان<br/>وراسمالي</lines>
    </verse>
    <verse name="v1c">
      <lines>ابن لي شأن كبير<br/>أبويا يبقى القدير<br/>إزاي أخاف أنا من الشرير<br/>مهما جاني</lines>
    </verse>
    <verse name="v1d">
      <lines>نساني الماضي الأليم<br/>خلى لساني يقول ترنيم<br/>غسلني بدمه الكريم<br/>وفداني</lines>
    </verse>
    <verse name="v1e">
      <lines>عوض عن كل اللي راح<br/>وضمد كل الجراح<br/>ويوماتي أعيش أفراح<br/>وأغاني</lines>
    </verse>
    <verse name="v1f">
      <lines>تعالوا شوفوا يا ناس<br/>يسوع إداني الخلاص<br/>ماشي معاه مرفوع الراس<br/>على مقامي</lines>
    </verse>
    <verse name="v1g">
      <lines>هاعيش له طول السنين<br/>ابن خاضع وأمين<br/>ولا أحيد عنه شمال ويمين<br/>طول أيامي</lines>
    </verse>
  </lyrics>
</song>
