<?xml version='1.0' encoding='UTF-8'?>
<song xmlns="http://openlyrics.info/namespace/2009/song" version="0.8" createdIn="OpenLP 2.4.6" modifiedIn="OpenLP 2.4.6" modifiedDate="2021-11-21T08:36:34">
  <properties>
    <titles>
      <title> أنا ليك</title>
    </titles>
    <comments>
      <comment>Unverfied Collection, Sourced From The Internet by Bill, On 20/11/2021 Contact Email:myway880@gmail.com
</comment>
    </comments>
    <authors>
      <author type="words">In Progress Collection</author>
    </authors>
  </properties>
  <lyrics>
    <verse name="v1a">
      <lines>حتى في عمري الصغير<br/>أنا ليك</lines>
    </verse>
    <verse name="v1b">
      <lines>قلبي مش هيتغير<br/>هيفضل ليك</lines>
    </verse>
    <verse name="v1c">
      <lines>وعمري لسه بيبتدي هابتديه معاك</lines>
    </verse>
    <verse name="v1d">
      <lines>وكل فحظة ف عمري أنا في حماك</lines>
    </verse>
    <verse name="v1e">
      <lines>أرشد خطواتي وقلبي في ضياك</lines>
    </verse>
    <verse name="v1f">
      <lines>وكل يوم في عمري هاعيشه ليك</lines>
    </verse>
    <verse name="v1g">
      <lines>أنا ليك<br/>أنا ليك<br/>هاباركك وأعليك وأعيش ليك</lines>
    </verse>
    <verse name="v1h">
      <lines>املا قلبي بالأغاني<br/>أنا مش لحد تاني</lines>
    </verse>
    <verse name="v1i">
      <lines>كل ساعات وثواني<br/>أنا ليك</lines>
    </verse>
    <verse name="v1j">
      <lines>أنا ليك<br/>أنا ليك<br/>هاباركك وأعليك وأعيش ليك</lines>
    </verse>
  </lyrics>
</song>
