<?xml version='1.0' encoding='UTF-8'?>
<song xmlns="http://openlyrics.info/namespace/2009/song" version="0.8" createdIn="OpenLP 2.4.6" modifiedIn="OpenLP 2.4.6" modifiedDate="2021-11-21T08:36:51">
  <properties>
    <titles>
      <title> اوعى تصدق صوت إبليس</title>
    </titles>
    <comments>
      <comment>Unverfied Collection, Sourced From The Internet by Bill, On 20/11/2021 Contact Email:myway880@gmail.com
</comment>
    </comments>
    <authors>
      <author type="words">In Progress Collection</author>
    </authors>
  </properties>
  <lyrics>
    <verse name="v1a">
      <lines>اوعى تصدق صوت إبليس لما يقولك لسه بدري<br/>ما هو قدامك عمر طويل افرح وافرح واجري<br/>خلي بالك أصل عدوك ده خاين كداب مكار<br/>عايزك تقضي معاه الأبدية هناك في جهنم وسط النار<br/>اوعى تصدق مهما يقول</lines>
    </verse>
    <verse name="v1b">
      <lines>اسمع صوت الرب ينادي ويقول يالا اليوم مقبول<br/>يالا اسمع صوته تعال تلقى عنده خلاص وقبول<br/>واللي هايسمع صوته وييجي راح ينضم مع الأبرار<br/>في السما راح يقضي الأبدية هناك في سعادة باستمرار<br/>يالا تعال اليوم مقبول</lines>
    </verse>
  </lyrics>
</song>
