<?xml version='1.0' encoding='UTF-8'?>
<song xmlns="http://openlyrics.info/namespace/2009/song" version="0.8" createdIn="OpenLP 2.4.6" modifiedIn="OpenLP 2.4.6" modifiedDate="2021-11-21T08:39:56">
  <properties>
    <titles>
      <title> يوم جديد</title>
    </titles>
    <comments>
      <comment>Unverfied Collection, Sourced From The Internet by Bill, On 20/11/2021 Contact Email:myway880@gmail.com
</comment>
    </comments>
    <authors>
      <author type="words">In Progress Collection</author>
    </authors>
  </properties>
  <lyrics>
    <verse name="v1">
      <lines>يوم جديد الدنيي عيد أنا كتي سعيد<br/>الرب عطاني نهار هداني تما كون عنو بعيد<br/>لأنو يسوع هو الط ر ي ق هوى الطريق<br/>لأنو يسوع المسيح هو الح ق هوي الحق<br/>لأنو يسوع هوي الح ي ا ة هوي الحياة<br/>هوي الطريق والحق والحياة<br/>متل الريشة أحلى عيشة في أو ما في شي<br/>الرب الراعي ما في داعي نعتمل هم كل شي<br/>دق الباب سماع جواب من قلب الكتاب<br/>كل يوم آية فيها حكاية محبة بلا حساب</lines>
    </verse>
  </lyrics>
</song>
