<?xml version='1.0' encoding='UTF-8'?>
<song xmlns="http://openlyrics.info/namespace/2009/song" version="0.8" createdIn="OpenLP 2.4.6" modifiedIn="OpenLP 2.4.6" modifiedDate="2021-11-21T08:35:57">
  <properties>
    <titles>
      <title> إله الأمانة</title>
    </titles>
    <comments>
      <comment>Unverfied Collection, Sourced From The Internet by Bill, On 20/11/2021 Contact Email:myway880@gmail.com
</comment>
    </comments>
    <authors>
      <author type="words">In Progress Collection</author>
    </authors>
  </properties>
  <lyrics>
    <verse name="v1a">
      <lines>إنت إلهنا إله الأمانة دايما معانا وبحب بترعانا</lines>
    </verse>
    <verse name="v1b">
      <lines>وفي كل لحظة وفي كل خطوة بنشوفك دايما بترشد خطانا</lines>
    </verse>
    <verse name="v1c">
      <lines>إله أمين ومالكش مثال وأمانتك ثابتة في كل الأحوال</lines>
    </verse>
    <verse name="v1d">
      <lines>دي حياتك لينا أحلى مثال هانعيش ونكون لك مهما العمر طال</lines>
    </verse>
    <verse name="v1e">
      <lines>إله أمين وهانتعلم منك إزاي نكون على صورتك وشبهك</lines>
    </verse>
    <verse name="v1f">
      <lines>ومن حياتك ومن كلماتك تغني حياتنا بأمانتك وصفاتك</lines>
    </verse>
    <verse name="v1g">
      <lines>إله أمين ودايما قريب ولا يوم تنسانا أو عنا تغيب</lines>
    </verse>
    <verse name="v1h">
      <lines>تعاليمك لينا سراج لرجلينا واللي يتمسك بيها عمره ما يخيب</lines>
    </verse>
  </lyrics>
</song>
