<?xml version='1.0' encoding='UTF-8'?>
<song xmlns="http://openlyrics.info/namespace/2009/song" version="0.8" createdIn="OpenLP 2.4.6" modifiedIn="OpenLP 2.4.6" modifiedDate="2021-11-21T08:41:21">
  <properties>
    <titles>
      <title> من بعدي ربي أنا عائد</title>
    </titles>
    <comments>
      <comment>Unverfied Collection, Sourced From The Internet by Bill, On 20/11/2021 Contact Email:myway880@gmail.com
</comment>
    </comments>
    <verseOrder>v1 c1 v2 c1 v3 c1 v4 c1</verseOrder>
    <authors>
      <author type="words">In Progress Collection</author>
    </authors>
  </properties>
  <lyrics>
    <verse name="v1">
      <lines>من بعدي ربي أنا عائد<br/>من الجوع والحرمان<br/>أمام حبك أنا ساجد<br/>أطرح خوفي والأحزان</lines>
    </verse>
    <verse name="c1">
      <lines> محتاج لإيدك تداويني<br/>مشتاق لحبك يسبيني<br/>وارويني منك ارويني<br/>فتحيا نفسي بعد ممات</lines>
    </verse>
    <verse name="v2">
      <lines> كل عهودي هي أوهام<br/>كل حياتي دونك لا تطيب<br/>كل ولائي هو أحلام<br/>كأني أحيا دون رقيب</lines>
    </verse>
    <verse name="v3">
      <lines> ماضيَّ فات سأنساه<br/>بأحزانه وشكواه<br/>يومي الآتي سأحياه<br/>أحيا لربي حتى لقاه</lines>
    </verse>
    <verse name="v4">
      <lines> أحيا لك على الدوام<br/>نفسي وقلبي والكِيان<br/>أصحو بك بعد المنام<br/>فالمس وقدِّس يا حنان</lines>
    </verse>
  </lyrics>
</song>
